{
  "report_name_format": "Crisis Room Aggregate Report",
  "input_recipe": {
    "query": {
      "ooi_types": [
        "IPAddressV6",
        "Hostname",
        "IPAddressV4",
        "URL"
      ],
      "scan_level": [
        1,
        2,
        3,
        4
      ],
      "scan_type": [
        "declared"
      ],
      "search_string": "",
      "order_by": "object_type",
      "asc_desc": "desc"
    }
  },
  "report_type": "aggregate-organisation-report",
  "asset_report_types": [
    "systems-report",
    "findings-report"
  ],
  "cron_expression": "0 * * * *"
}
